ALU/src/alu.vhd
--libraries 
library ieee;
use ieee.std_logic_1164.all;
--entity
entity alu is 
    port(X : in std_logic_vector (7 downto 0);
        Y : in std_logic_vector (7 downto 0);
        opera : in std_logic_vector (1 downto 0);
        result : out std_logic_vector (7 downto 0)
    );
end alu;
--architecture
architecture Behavioral of alu is 
begin
    with opera select
        result <= X or Y when "00",
               X and Y   when "01",
               X         when "10",
               Y         when others;
             

end Behavioral;

ALU/tb/alutb.vhd
library ieee;
use ieee.std_logic_1164.all;
--entity
entity alutb is 
end alutb;
--architecture
architecture Behavioral of alutb is 
    --INPUTS
    signal Xx: std_logic_vector(7 downto 0):= (others => '0');
    signal Yy: std_logic_vector(7 downto 0):= (others => '0');
    signal operacion : std_logic_vector(1 downto 0):= (others => '0');
   -- OUTPUTS

   signal resultado : std_logic_vector(7 downto 0);

    component alu is
        port(X : in std_logic_vector (7 downto 0);
            Y : in std_logic_vector (7 downto 0);
            opera : in std_logic_vector (1 downto 0);
            result : out std_logic_vector (7 downto 0)
        );
        

    end component;

    begin 
    --instancio circuito
    alu1: alu port map(
        X => Xx,
        Y => Yy,
        opera => operacion,
        result => resultado
    );
    
    process is 
        begin
        

        Xx <= "00001000";  --8
        Yy <= "00000100";  --4
        operacion <= "00";  --and
        wait for 100 ns; 
        
        Xx <= "00001000";  --8
        Yy <= "00000100";  --4
        operacion <= "01";  -- or
        wait for 100 ns; 

        Xx <= "00001000";  --8
        Yy <= "00000100";  --4
        operacion <= "10";  -- X
        wait for 100 ns; 

        Xx <= "00001000";  --8
        Yy <= "00000100";  --4
        operacion <= "11";  -- Y
        wait for 100 ns; 
    end process;


end Behavioral;

ALU/sim/alutb.vcd
$date
  Tue Dec 27 18:24:21 2022
$end
$version
  GHDL v0
$end
$timescale
  1 fs
$end
$scope module standard $end
$upscope $end
$scope module std_logic_1164 $end
$upscope $end
$scope module alutb $end
$var reg 8 ! xx[7:0] $end
$var reg 8 " yy[7:0] $end
$var reg 2 # operacion[1:0] $end
$var reg 8 $ resultado[7:0] $end
$scope module alu1 $end
$var reg 8 % x[7:0] $end
$var reg 8 & y[7:0] $end
$var reg 2 ' opera[1:0] $end
$var reg 8 ( result[7:0] $end
$upscope $end
$upscope $end
$enddefinitions $end
#0
b00001000 !
b00000100 "
b00 #
b00001100 $
b00001000 %
b00000100 &
b00 '
b00001100 (
#100000000
b01 #
b00000000 $
b01 '
b00000000 (
#200000000
b10 #
b00001000 $
b10 '
b00001000 (
#300000000
b11 #
b00000100 $
b11 '
b00000100 (
#400000000
b00 #
b00001100 $
b00 '
b00001100 (
#500000000
b01 #
b00000000 $
b01 '
b00000000 (
#600000000
b10 #
b00001000 $
b10 '
b00001000 (
#700000000
b11 #
b00000100 $
b11 '
b00000100 (
#800000000
b00 #
b00001100 $
b00 '
b00001100 (
#900000000
b01 #
b00000000 $
b01 '
b00000000 (
#1000000000
b10 #
b00001000 $
b10 '
b00001000 (
