GateOr/src/gate_or.vhd
--COMPUERTA OR
--Librerias
library ieee;
use ieee.std_logic_1164.all;


--Entidad
entity gate_or is 
    port(entrada1 : in std_logic;
            entrada2 : in std_logic;
            salida : out std_logic 
    );
end gate_or;


--arquitectura

architecture Behavioral of gate_or is 
begin 
salida <= entrada1 or entrada2;

end Behavioral;

GateOr/tb/gate_ortb.vhd
--librerias

library ieee;
use ieee.std_logic_1164.all;


--Entidad

entity gate_ortb is 
end gate_ortb;    
 
--Arquitectura
architecture Behavioral of gate_ortb is
    signal Ab:   std_logic:='0';
    signal Bc:   std_logic:='0';
    signal De:   std_logic;

    --circuito a testear  definicion estructural
component gate_or is 
    port(entrada1 : in std_logic;
            entrada2 : in std_logic;
            salida : out std_logic);
end component; 

begin
    --instanciar circuito a testet
    u1: gate_or port map(entrada1 =>Ab,
                        entrada2 =>Bc,
                        salida=>De
                        );   -- descripcion estructural
    --generar estimulos
    process is   ---descripcion comportamental
        begin
        Ab <= '0';
        Bc <= '0';
        wait for 10 ns; 
        Ab <= '0';
        Bc <= '1';
        wait for 10 ns; 
        Ab <= '1';
        Bc <= '0';
        wait for 10 ns; 
        Ab <= '1';
        Bc <= '1';
        wait for 10 ns; 
    end process;
end Behavioral;

GateOr/sim/gate_ortb.vcd
$date
  Mon Dec 26 12:07:38 2022
$end
$version
  GHDL v0
$end
$timescale
  1 fs
$end
$scope module standard $end
$upscope $end
$scope module std_logic_1164 $end
$upscope $end
$scope module gate_ortb $end
$var reg 1 ! ab $end
$var reg 1 " bc $end
$var reg 1 # de $end
$scope module u1 $end
$var reg 1 $ entrada1 $end
$var reg 1 % entrada2 $end
$var reg 1 & salida $end
$upscope $end
$upscope $end
$enddefinitions $end
#0
0!
0"
0#
0$
0%
0&
#10000000
1"
1#
1%
1&
#20000000
1!
0"
1$
0%
#30000000
1"
1%
#40000000
0!
0"
0#
0$
0%
0&
#50000000
1"
1#
1%
1&
#60000000
1!
0"
1$
0%
#70000000
1"
1%
#80000000
0!
0"
0#
0$
0%
0&
#90000000
1"
1#
1%
1&
#100000000
1!
0"
1$
0%
#110000000
1"
1%
#120000000
0!
0"
0#
0$
0%
0&
#130000000
1"
1#
1%
1&
#140000000
1!
0"
1$
0%
#150000000
1"
1%
#160000000
0!
0"
0#
0$
0%
0&
#170000000
1"
1#
1%
1&
#180000000
1!
0"
1$
0%
#190000000
1"
1%
#200000000
0!
0"
0#
0$
0%
0&
#210000000
1"
1#
1%
1&
#220000000
1!
0"
1$
0%
#230000000
1"
1%
#240000000
0!
0"
0#
0$
0%
0&
#250000000
1"
1#
1%
1&
#260000000
1!
0"
1$
0%
#270000000
1"
1%
#280000000
0!
0"
0#
0$
0%
0&
#290000000
1"
1#
1%
1&
#300000000
1!
0"
1$
0%
#310000000
1"
1%
#320000000
0!
0"
0#
0$
0%
0&
#330000000
1"
1#
1%
1&
#340000000
1!
0"
1$
0%
#350000000
1"
1%
#360000000
0!
0"
0#
0$
0%
0&
#370000000
1"
1#
1%
1&
#380000000
1!
0"
1$
0%
#390000000
1"
1%
#400000000
0!
0"
0#
0$
0%
0&
#410000000
1"
1#
1%
1&
#420000000
1!
0"
1$
0%
#430000000
1"
1%
#440000000
0!
0"
0#
0$
0%
0&
#450000000
1"
1#
1%
1&
#460000000
1!
0"
1$
0%
#470000000
1"
1%
#480000000
0!
0"
0#
0$
0%
0&
#490000000
1"
1#
1%
1&
#500000000
1!
0"
1$
0%
#510000000
1"
1%
#520000000
0!
0"
0#
0$
0%
0&
#530000000
1"
1#
1%
1&
#540000000
1!
0"
1$
0%
#550000000
1"
1%
#560000000
0!
0"
0#
0$
0%
0&
#570000000
1"
1#
1%
1&
#580000000
1!
0"
1$
0%
#590000000
1"
1%
#600000000
0!
0"
0#
0$
0%
0&
#610000000
1"
1#
1%
1&
#620000000
1!
0"
1$
0%
#630000000
1"
1%
#640000000
0!
0"
0#
0$
0%
0&
#650000000
1"
1#
1%
1&
#660000000
1!
0"
1$
0%
#670000000
1"
1%
#680000000
0!
0"
0#
0$
0%
0&
#690000000
1"
1#
1%
1&
#700000000
1!
0"
1$
0%
#710000000
1"
1%
#720000000
0!
0"
0#
0$
0%
0&
#730000000
1"
1#
1%
1&
#740000000
1!
0"
1$
0%
#750000000
1"
1%
#760000000
0!
0"
0#
0$
0%
0&
#770000000
1"
1#
1%
1&
#780000000
1!
0"
1$
0%
#790000000
1"
1%
#800000000
0!
0"
0#
0$
0%
0&
#810000000
1"
1#
1%
1&
#820000000
1!
0"
1$
0%
#830000000
1"
1%
#840000000
0!
0"
0#
0$
0%
0&
#850000000
1"
1#
1%
1&
#860000000
1!
0"
1$
0%
#870000000
1"
1%
#880000000
0!
0"
0#
0$
0%
0&
#890000000
1"
1#
1%
1&
#900000000
1!
0"
1$
0%
#910000000
1"
1%
#920000000
0!
0"
0#
0$
0%
0&
#930000000
1"
1#
1%
1&
#940000000
1!
0"
1$
0%
#950000000
1"
1%
#960000000
0!
0"
0#
0$
0%
0&
#970000000
1"
1#
1%
1&
#980000000
1!
0"
1$
0%
#990000000
1"
1%
#1000000000
0!
0"
0#
0$
0%
0&
